{"code": 0, "data": [{"cid": 2904390, "deleted": false, "image_metadata": {}, "is_dz": true, "name": "洞主", "pid": 446181, "reply_to": -1, "tag": null, "text": "银英bot在树洞危急存亡之秋来做存档，做到这天链表断了，也不能搜索，emo了", "timestamp": 1636525626, "type": "text", "url": ""}], "post": {"deleted": false, "image_metadata": {"h": 3167, "w": 1578}, "likenum": 1, "pid": 446181, "reply": 1, "tag": null, "text": "#银英110问 day8\n杨舰队玩笑（？）三人组中好感度最高的是哪位？\n\n---\n（推荐屏蔽词：“银英110问”）\n\n\\\n差点就断更了www\n\n\\\n上一期图片令人不适（奥贝斯坦遗容），就不引用了，该打个码来着orz\n\n\\\n本来想要每人一张ova截图一张帅照的，找了半天也没找到波布兰英俊的照片w", "timestamp": 1629555057, "type": "image", "updated_at": 1636525626, "url": "ly/lymekvpungf7rkbzbsy3a55g3shxmw5v.jpeg", "vote": {"vote_data": {"华尔特·冯·先寇布": 1, "达斯提·亚典波罗": 1, "奥利比·波布兰": 0, "瓜": 10}, "vote_options": ["华尔特·冯·先寇布", "达斯提·亚典波罗", "奥利比·波布兰", "瓜"]}}}