{"code": 0, "data": [{"cid": 1076072, "deleted": false, "image_metadata": {}, "is_dz": false, "name": "Alice", "pid": 211613, "reply_to": -1, "tag": null, "text": "高富帅能豪车接送古驰，你清华男有什么？", "timestamp": 1612980325, "type": "text", "url": ""}, {"cid": 1076085, "deleted": false, "image_metadata": {}, "is_dz": false, "name": "Bob", "pid": 211613, "reply_to": -1, "tag": null, "text": "崇拜yp咋了?一千零一夜难道不是好书吗", "timestamp": 1612981269, "type": "text", "url": ""}], "post": {"deleted": false, "image_metadata": {}, "likenum": 1, "pid": 211613, "reply": 2, "tag": null, "text": "喷清华男利用学历崇拜 yp，和喷高富帅利用拜金/颜控心理 yp，本质上其实都是酸吧？", "timestamp": 1612979510, "type": "text", "updated_at": 1612981271, "url": "", "vote": {}}}