{"code": 0, "data": [{"cid": 479507, "deleted": false, "image_metadata": {}, "is_dz": false, "name": "Alice", "pid": 99581, "reply_to": -1, "tag": null, "text": "有吧", "timestamp": 1603427302, "type": "text", "url": ""}, {"cid": 479900, "deleted": false, "image_metadata": {}, "is_dz": false, "name": "Bob", "pid": 99581, "reply_to": -1, "tag": null, "text": "几字班的", "timestamp": 1603434183, "type": "text", "url": ""}, {"cid": 480060, "deleted": false, "image_metadata": {}, "is_dz": true, "name": "洞主", "pid": 99581, "reply_to": -1, "tag": null, "text": "Re : 八字班", "timestamp": 1603437775, "type": "text", "url": ""}, {"cid": 480064, "deleted": false, "image_metadata": {}, "is_dz": true, "name": "洞主", "pid": 99581, "reply_to": -1, "tag": null, "text": "Re Alice: 怎么有的洞说没有，她是不是之前分手了", "timestamp": 1603437806, "type": "text", "url": ""}, {"cid": 480186, "deleted": false, "image_metadata": {}, "is_dz": false, "name": "Carol", "pid": 99581, "reply_to": -1, "tag": null, "text": "薛定谔的男朋友", "timestamp": 1603440219, "type": "text", "url": ""}, {"cid": 481094, "deleted": false, "image_metadata": {}, "is_dz": false, "name": "Dave", "pid": 99581, "reply_to": -1, "tag": null, "text": "大部分时间有 加油", "timestamp": 1603459768, "type": "text", "url": ""}, {"cid": 481177, "deleted": false, "image_metadata": {}, "is_dz": false, "name": "Eve", "pid": 99581, "reply_to": -1, "tag": null, "text": "Re Dave: ?", "timestamp": 1603462549, "type": "text", "url": ""}, {"cid": 481635, "deleted": false, "image_metadata": {}, "is_dz": true, "name": "洞主", "pid": 99581, "reply_to": -1, "tag": null, "text": "Re Dave: ？", "timestamp": 1603471429, "type": "text", "url": ""}], "post": {"deleted": false, "image_metadata": {}, "likenum": 5, "pid": 99581, "reply": 8, "tag": null, "text": "法学院lx同学有npy吗？不是故意要八卦，只是不敢鲁莽搭讪xjj", "timestamp": 1603425435, "type": "text", "updated_at": 1606782637, "url": "", "vote": {}}}