{"code": 0, "data": [{"cid": 1485787, "deleted": false, "image_metadata": {}, "is_dz": false, "name": "Alice", "pid": 292032, "reply_to": -1, "tag": null, "text": "Alice", "timestamp": 1618899075, "type": "text", "url": ""}, {"cid": 1489252, "deleted": false, "image_metadata": {}, "is_dz": false, "name": "Bob", "pid": 292032, "reply_to": -1, "tag": null, "text": "Bob", "timestamp": 1618927723, "type": "text", "url": ""}], "post": {"deleted": false, "image_metadata": {}, "likenum": 1, "pid": 292032, "reply": 2, "tag": null, "text": "贵八特奖候选人提名洞", "timestamp": 1618895609, "type": "text", "updated_at": 1618927723, "url": "", "vote": {}}}