{"code": 0, "data": [{"cid": 2054926, "deleted": false, "image_metadata": {}, "is_dz": true, "name": "洞主", "pid": 400897, "reply_to": -1, "tag": null, "text": "诸多的学习道路之中，通过往年题进行拟合是最便利而封闭的路径", "timestamp": 1626115706, "type": "text", "url": ""}, {"cid": 2054928, "deleted": false, "image_metadata": {}, "is_dz": false, "name": "Alice", "pid": 400897, "reply_to": -1, "tag": null, "text": "确实啊", "timestamp": 1626115768, "type": "text", "url": ""}, {"cid": 2054933, "deleted": false, "image_metadata": {}, "is_dz": false, "name": "Bob", "pid": 400897, "reply_to": -1, "tag": null, "text": "那不是学习的道路 是卷gpa的道路", "timestamp": 1626115820, "type": "text", "url": ""}, {"cid": 2055133, "deleted": false, "image_metadata": {}, "is_dz": false, "name": "Carol", "pid": 400897, "reply_to": -1, "tag": null, "text": "多高\n", "timestamp": 1626135439, "type": "text", "url": ""}], "post": {"deleted": false, "image_metadata": {"h": 626, "w": 632}, "likenum": 1, "pid": 400897, "reply": 4, "tag": "令人不适", "text": "睡了两年觉，打了两千多小时游戏，只获得一个高绩点的我一无所有。唉，只有智商是多么可悲，简单的东西看一遍就会了，真是不懂那些去上课了还要课下额外花时间的人是怎么学的。\n（发这个就是虚空嘲讽一下学了一年才有个高绩点的，至少我快乐了，虽然我也一无所有）\n认真的说，我觉得大范围公布资料是善行，总比一部分人找到学长要往年题导致成绩出现差异的情况要好。他本人也是受到了一些挫折才这样做，没啥好骂的。", "timestamp": 1626115630, "type": "image", "updated_at": 1626135438, "url": "qz/qzszp46haowiz7tzl437pvbhziiqnwly.jpeg", "vote": {}}}