{"code": 0, "data": [{"cid": 1233021, "deleted": false, "image_metadata": {}, "is_dz": false, "name": "Alice", "pid": 243079, "reply_to": -1, "tag": null, "text": "emmm，，如果爸爸是司机，妈妈是临时工算不算？", "timestamp": 1615373823, "type": "text", "url": ""}, {"cid": 1233031, "deleted": false, "image_metadata": {}, "is_dz": false, "name": "Bob", "pid": 243079, "reply_to": -1, "tag": null, "text": "和alice一样\n", "timestamp": 1615373907, "type": "text", "url": ""}, {"cid": 1233035, "deleted": false, "image_metadata": {}, "is_dz": true, "name": "洞主", "pid": 243079, "reply_to": -1, "tag": null, "text": "Re Alice: 体制外无固定职业，无保险，从事体力劳动者都算", "timestamp": 1615373931, "type": "text", "url": ""}, {"cid": 1233041, "deleted": false, "image_metadata": {}, "is_dz": true, "name": "洞主", "pid": 243079, "reply_to": -1, "tag": null, "text": "Re 洞主: 保险特指社保", "timestamp": 1615373967, "type": "text", "url": ""}, {"cid": 1233069, "deleted": false, "image_metadata": {}, "is_dz": true, "name": "洞主", "pid": 243079, "reply_to": -1, "tag": null, "text": "一个鲜明的特征就是疫情隔离期间无工资，看病需要自掏腰包", "timestamp": 1615374111, "type": "text", "url": ""}, {"cid": 1234190, "deleted": false, "image_metadata": {}, "is_dz": false, "name": "Alice", "pid": 243079, "reply_to": -1, "tag": null, "text": "Re 洞主: hh，疫情期间（3月之后）我爸还是得去运货，因为物流不能完全停滞（饲料之类的）", "timestamp": 1615384580, "type": "text", "url": ""}, {"cid": 1234267, "deleted": false, "image_metadata": {}, "is_dz": true, "name": "洞主", "pid": 243079, "reply_to": -1, "tag": null, "text": "Re Alice: 哦哦，确实有这个情况", "timestamp": 1615385210, "type": "text", "url": ""}], "post": {"deleted": false, "image_metadata": {}, "likenum": 1, "pid": 243079, "reply": 7, "tag": null, "text": "大家有多少是农民工或者下岗工人子女呀？纯好奇 dz就是", "timestamp": 1615373651, "type": "text", "updated_at": 1615385211, "url": "", "vote": {}}}