{"code": 0, "data": [{"cid": 1234165, "deleted": false, "image_metadata": {}, "is_dz": false, "name": "Bob", "pid": 243273, "reply_to": -1, "tag": null, "text": "Alice中肯", "timestamp": 1615384334, "type": "text", "url": ""}, {"cid": 1234168, "deleted": false, "image_metadata": {}, "is_dz": false, "name": "Carol", "pid": 243273, "reply_to": -1, "tag": null, "text": "alice精准", "timestamp": 1615384353, "type": "text", "url": ""}, {"cid": 1234171, "deleted": false, "image_metadata": {}, "is_dz": false, "name": "Dave", "pid": 243273, "reply_to": -1, "tag": null, "text": "红红火火恍恍惚惚", "timestamp": 1615384402, "type": "text", "url": ""}, {"cid": 1234173, "deleted": false, "image_metadata": {}, "is_dz": false, "name": "Eve", "pid": 243273, "reply_to": -1, "tag": null, "text": "Alice说得好", "timestamp": 1615384416, "type": "text", "url": ""}, {"cid": 1234205, "deleted": false, "image_metadata": {}, "is_dz": true, "name": "洞主", "pid": 243273, "reply_to": -1, "tag": null, "text": "Re Eve: ？？", "timestamp": 1615384680, "type": "text", "url": ""}, {"cid": 1234210, "deleted": false, "image_metadata": {}, "is_dz": true, "name": "洞主", "pid": 243273, "reply_to": -1, "tag": null, "text": "是已经约了别的妹子，不是我想约别的妹子", "timestamp": 1615384699, "type": "text", "url": ""}, {"cid": 1234273, "deleted": false, "image_metadata": {}, "is_dz": false, "name": "Francis", "pid": 243273, "reply_to": -1, "tag": null, "text": "Nt nice try", "timestamp": 1615385255, "type": "text", "url": ""}, {"cid": 1234344, "deleted": false, "image_metadata": {}, "is_dz": true, "name": "洞主", "pid": 243273, "reply_to": -1, "tag": null, "text": "Re Francis: ？", "timestamp": 1615385725, "type": "text", "url": ""}, {"cid": 1234432, "deleted": false, "image_metadata": {}, "is_dz": false, "name": "Grace", "pid": 243273, "reply_to": -1, "tag": null, "text": "Alice 真棒", "timestamp": 1615386538, "type": "text", "url": ""}], "post": {"deleted": false, "image_metadata": {}, "likenum": 0, "pid": 243273, "reply": 9, "tag": null, "text": "#243256\n哼，我约别的妹子了，老子还非你不可嘛真是的", "timestamp": 1615384255, "type": "text", "updated_at": 1615387376, "url": "", "vote": {}}}