{"code": 0, "data": [{"cid": 1236412, "deleted": false, "image_metadata": {}, "is_dz": false, "name": "Alice", "pid": 243652, "reply_to": -1, "tag": null, "text": "奖学金一般是一年以内的论文吧", "timestamp": 1615428584, "type": "text", "url": ""}, {"cid": 1236414, "deleted": false, "image_metadata": {}, "is_dz": true, "name": "洞主", "pid": 243652, "reply_to": -1, "tag": null, "text": "比如院系的年度人物和学校的年度人物。dz觉得会不会不好", "timestamp": 1615428598, "type": "text", "url": ""}, {"cid": 1236420, "deleted": false, "image_metadata": {}, "is_dz": true, "name": "洞主", "pid": 243652, "reply_to": -1, "tag": null, "text": "Re Alice: 啊好吧，其实不是这个意思hhh。所以加了引号", "timestamp": 1615428640, "type": "text", "url": ""}, {"cid": 1236441, "deleted": false, "image_metadata": {}, "is_dz": false, "name": "Bob", "pid": 243652, "reply_to": -1, "tag": null, "text": "Re 洞主: 这俩一起申完全没问题吧", "timestamp": 1615429086, "type": "text", "url": ""}, {"cid": 1236494, "deleted": false, "image_metadata": {}, "is_dz": false, "name": "Carol", "pid": 243652, "reply_to": -1, "tag": null, "text": "Re Bob: Re Bob: 我也觉得，这也不能算“一稿多投”吧", "timestamp": 1615429812, "type": "text", "url": ""}, {"cid": 1236682, "deleted": false, "image_metadata": {}, "is_dz": true, "name": "洞主", "pid": 243652, "reply_to": -1, "tag": null, "text": "Re Bob: 啊啊好的。谢谢大家", "timestamp": 1615431792, "type": "text", "url": ""}, {"cid": 1236707, "deleted": false, "image_metadata": {}, "is_dz": true, "name": "洞主", "pid": 243652, "reply_to": -1, "tag": null, "text": "Re Carol: 嗯，这就去申ME的", "timestamp": 1615432042, "type": "text", "url": ""}], "post": {"deleted": false, "image_metadata": {}, "likenum": 3, "pid": 243652, "reply": 7, "tag": null, "text": "申请一些荣誉的时候可以“一稿多投”么？还是说攒着申请大荣誉呢？", "timestamp": 1615428548, "type": "text", "updated_at": 1615432043, "url": "", "vote": {}}}