{"code": 0, "data": [{"cid": 351131, "deleted": false, "image_metadata": {}, "is_dz": false, "name": "Alice", "pid": 70960, "reply_to": -1, "tag": null, "text": "感觉效果可能也不好，不如单空出来两星期让我缓缓", "timestamp": 1600096979, "type": "text", "url": ""}, {"cid": 351427, "deleted": false, "image_metadata": {}, "is_dz": true, "name": "洞主", "pid": 70960, "reply_to": -1, "tag": null, "text": "两周还是太少了 减个肥时间都不够的", "timestamp": 1600099604, "type": "text", "url": ""}], "post": {"deleted": false, "image_metadata": {}, "likenum": 1, "pid": 70960, "reply": 2, "tag": null, "text": "如果工作之前你有一年的时间可以自由支配 你会选择干哪些事情？自我提升方面的", "timestamp": 1600096806, "type": "text", "updated_at": 1606782618, "url": "", "vote": {}}}