{"code": 0, "data": [{"cid": 3135777, "deleted": false, "image_metadata": {}, "is_dz": false, "name": "Alice", "pid": 593526, "reply_to": -1, "tag": null, "text": "是小好不是大好", "timestamp": 1638962593, "type": "text", "url": ""}], "post": {"deleted": false, "image_metadata": {}, "likenum": 0, "pid": 593526, "reply": 1, "tag": null, "text": "树洞被墙，是不是比原来更合适/doge", "timestamp": 1638962417, "type": "text", "updated_at": 1638962594, "url": "", "vote": {"vote_data": {"好": 82, "不好": 21, "瓜": 35}, "vote_options": ["好", "不好", "瓜"]}}}