{"code": 0, "data": [{"cid": 961452, "deleted": false, "image_metadata": {}, "is_dz": false, "name": "Alice", "pid": 194974, "reply_to": -1, "tag": null, "text": "刷0", "timestamp": 1611321778, "type": "text", "url": ""}, {"cid": 961457, "deleted": false, "image_metadata": {}, "is_dz": false, "name": "Bob", "pid": 194974, "reply_to": -1, "tag": null, "text": "直接放弃避免受罪", "timestamp": 1611321793, "type": "text", "url": ""}, {"cid": 961480, "deleted": false, "image_metadata": {}, "is_dz": false, "name": "Carol", "pid": 194974, "reply_to": -1, "tag": null, "text": "也就-20而已，跟老师求求情还是能过的", "timestamp": 1611321916, "type": "text", "url": ""}, {"cid": 961897, "deleted": false, "image_metadata": {}, "is_dz": false, "name": "Dave", "pid": 194974, "reply_to": -1, "tag": null, "text": "多大算大体重？我180cm 80kg练了一学期到满分了", "timestamp": 1611323272, "type": "text", "url": ""}], "post": {"deleted": false, "image_metadata": {}, "likenum": 0, "pid": 194974, "reply": 4, "tag": null, "text": "树洞里大体重的xdm是怎么解决体育课引体向上的问题的？", "timestamp": 1611321751, "type": "text", "updated_at": 1611323273, "url": "", "vote": {}}}