{"code": 0, "data": [{"cid": 2191163, "deleted": false, "image_metadata": {}, "is_dz": false, "name": "Alice", "pid": 424474, "reply_to": -1, "tag": null, "text": "第二次", "timestamp": 1627891351, "type": "text", "url": ""}, {"cid": 2191175, "deleted": false, "image_metadata": {}, "is_dz": false, "name": "Bob", "pid": 424474, "reply_to": -1, "tag": null, "text": "第三次", "timestamp": 1627891481, "type": "text", "url": ""}, {"cid": 2191223, "deleted": false, "image_metadata": {}, "is_dz": false, "name": "Carol", "pid": 424474, "reply_to": -1, "tag": null, "text": "第三次", "timestamp": 1627892000, "type": "text", "url": ""}, {"cid": 2191335, "deleted": false, "image_metadata": {}, "is_dz": false, "name": "Dave", "pid": 424474, "reply_to": -1, "tag": null, "text": "第一次", "timestamp": 1627892997, "type": "text", "url": ""}], "post": {"deleted": false, "image_metadata": {}, "likenum": 3, "pid": 424474, "reply": 4, "tag": null, "text": "约会几次会表白？", "timestamp": 1627890811, "type": "text", "updated_at": 1627892998, "url": "", "vote": {}}}