{"code": 0, "data": [{"cid": 402688, "deleted": false, "image_metadata": {}, "is_dz": false, "name": "Alice", "pid": 83234, "reply_to": -1, "tag": null, "text": "想带就带", "timestamp": 1601465824, "type": "text", "url": ""}, {"cid": 402699, "deleted": false, "image_metadata": {}, "is_dz": false, "name": "Bob", "pid": 83234, "reply_to": -1, "tag": null, "text": "不合适", "timestamp": 1601466068, "type": "text", "url": ""}, {"cid": 402701, "deleted": false, "image_metadata": {}, "is_dz": true, "name": "洞主", "pid": 83234, "reply_to": -1, "tag": null, "text": "Re Bob: 为啥不合适呀", "timestamp": 1601466113, "type": "text", "url": ""}, {"cid": 402740, "deleted": false, "image_metadata": {}, "is_dz": false, "name": "Carol", "pid": 83234, "reply_to": -1, "tag": null, "text": "Re 洞主: 人有点少吧感觉，一共才8个人那应该都挺熟的，大家聚聚一起玩玩聊聊以前，多一个不熟悉的人怪尴尬的", "timestamp": 1601467067, "type": "text", "url": ""}, {"cid": 402746, "deleted": false, "image_metadata": {}, "is_dz": true, "name": "洞主", "pid": 83234, "reply_to": -1, "tag": null, "text": "Re Carol: 谢谢Carol", "timestamp": 1601467129, "type": "text", "url": ""}, {"cid": 402811, "deleted": false, "image_metadata": {}, "is_dz": false, "name": "Dave", "pid": 83234, "reply_to": -1, "tag": null, "text": "别吧，难道让npy在一边尴尬么", "timestamp": 1601468291, "type": "text", "url": ""}], "post": {"deleted": false, "image_metadata": {}, "likenum": 3, "pid": 83234, "reply": 6, "tag": null, "text": "dz国庆有高中同学聚会，想带npy去，不知道合适不合适，总共大概8个人，有一个人认识npy", "timestamp": 1601465793, "type": "text", "updated_at": 1606782626, "url": "", "vote": {}}}