{"code": 0, "data": [{"cid": 2375265, "deleted": false, "image_metadata": {}, "is_dz": false, "name": "Alice", "pid": 453691, "reply_to": -1, "tag": null, "text": "没错", "timestamp": 1630139474, "type": "text", "url": ""}, {"cid": 2375271, "deleted": false, "image_metadata": {}, "is_dz": false, "name": "Bob", "pid": 453691, "reply_to": -1, "tag": null, "text": "其实5G也不一定得有，但校确实一定要出", "timestamp": 1630139499, "type": "text", "url": ""}, {"cid": 2375303, "deleted": false, "image_metadata": {}, "is_dz": false, "name": "Carol", "pid": 453691, "reply_to": -1, "tag": null, "text": "我每天都出去，要憋疯了", "timestamp": 1630139752, "type": "text", "url": ""}, {"cid": 2375309, "deleted": false, "image_metadata": {}, "is_dz": false, "name": "Carol", "pid": 453691, "reply_to": -1, "tag": null, "text": "#453689洞主", "timestamp": 1630139772, "type": "text", "url": ""}, {"cid": 2375474, "deleted": false, "image_metadata": {}, "is_dz": true, "name": "洞主", "pid": 453691, "reply_to": 2375271, "tag": null, "text": "Re Bob: 现在卖的智能手机没有5G的除了huawei没别的了应该", "timestamp": 1630140835, "type": "text", "url": ""}, {"cid": 2375477, "deleted": false, "image_metadata": {}, "is_dz": true, "name": "洞主", "pid": 453691, "reply_to": 2375271, "tag": null, "text": "Re Bob: 华为卖个4G还被老多人说智商税呢", "timestamp": 1630140856, "type": "text", "url": ""}, {"cid": 2375554, "deleted": false, "image_metadata": {}, "is_dz": false, "name": "Dave", "pid": 453691, "reply_to": 2375477, "tag": null, "text": "不就是智商税吗...叫水滴筹机型更好听？", "timestamp": 1630141367, "type": "text", "url": ""}], "post": {"deleted": false, "image_metadata": {}, "likenum": 3, "pid": 453691, "reply": 7, "tag": null, "text": "封校就像现在买新手机有5G一样\n5G不一定用得上，但是一定得有；出校不一定经常出，但是一定得能出", "timestamp": 1630139267, "type": "text", "updated_at": 1630141365, "url": "", "vote": {}}}