{"code": 0, "data": [{"cid": 2934565, "deleted": false, "image_metadata": {}, "is_dz": false, "name": "Alice", "pid": 557804, "reply_to": -1, "tag": null, "text": "后疫情时代，摊手.jpg", "timestamp": 1636867213, "type": "text", "url": ""}, {"cid": 2934576, "deleted": false, "image_metadata": {}, "is_dz": false, "name": "Bob", "pid": 557804, "reply_to": -1, "tag": null, "text": "花点钱找人打断他的胳膊腿", "timestamp": 1636867257, "type": "text", "url": ""}, {"cid": 2934587, "deleted": false, "image_metadata": {}, "is_dz": false, "name": "Carol", "pid": 557804, "reply_to": -1, "tag": null, "text": "私有财产神圣不可侵犯", "timestamp": 1636867351, "type": "text", "url": ""}], "post": {"deleted": false, "image_metadata": {}, "likenum": 2, "pid": 557804, "reply": 3, "tag": null, "text": "uu们怎么评价？\nhttps://m.bilibili.com/video/BV1oQ4y1m7fz?p=1&share_medium=android&share_plat=android&share_session_id=3cc562fa-6da6-410c-bbdd-22a4ee698f73&share_source=WEIXIN&share_tag=s_i&timestamp=1636866314&unique_k=WrBveB", "timestamp": 1636867154, "type": "text", "updated_at": 1636867351, "url": "", "vote": {}}}