{"code": 0, "data": [{"cid": 499504, "deleted": false, "image_metadata": {}, "is_dz": false, "name": "Alice", "pid": 103961, "reply_to": -1, "tag": null, "text": "原则上是只要发票，有开药的话也要带上处方，发票打印不清晰的最好在北医三院自助机上打一下收费明细。记得在清华后勤公众号预约。现在去报销的地方要走急诊上二楼，具体怎么走可以去校医院门口问护士", "timestamp": 1603965029, "type": "text", "url": ""}, {"cid": 499510, "deleted": false, "image_metadata": {}, "is_dz": false, "name": "Bob", "pid": 103961, "reply_to": -1, "tag": null, "text": "是只需要黄色收据吧", "timestamp": 1603965107, "type": "text", "url": ""}, {"cid": 499533, "deleted": false, "image_metadata": {}, "is_dz": false, "name": "Alice", "pid": 103961, "reply_to": -1, "tag": null, "text": "对了黄色的那张就是发票", "timestamp": 1603965578, "type": "text", "url": ""}, {"cid": 499569, "deleted": false, "image_metadata": {}, "is_dz": true, "name": "洞主", "pid": 103961, "reply_to": -1, "tag": null, "text": "谢谢Alice和Bob！", "timestamp": 1603966229, "type": "text", "url": ""}, {"cid": 499571, "deleted": false, "image_metadata": {}, "is_dz": true, "name": "洞主", "pid": 103961, "reply_to": -1, "tag": null, "text": "Re Alice: 好的！", "timestamp": 1603966257, "type": "text", "url": ""}], "post": {"deleted": false, "image_metadata": {}, "likenum": 3, "pid": 103961, "reply": 5, "tag": null, "text": "看到有人说北医三院报销需要发票， 只有黄色的收据可以吗？ 转院单已经有了，就诊完了，是去校医院哪里报销呢？", "timestamp": 1603964219, "type": "text", "updated_at": 1606782636, "url": "", "vote": {}}}