{"code": 0, "data": [{"cid": 1014317, "deleted": false, "image_metadata": {}, "is_dz": false, "name": "Alice", "pid": 202191, "reply_to": -1, "tag": null, "text": "分", "timestamp": 1611919581, "type": "text", "url": ""}, {"cid": 1014325, "deleted": false, "image_metadata": {}, "is_dz": false, "name": "Bob", "pid": 202191, "reply_to": -1, "tag": null, "text": "如果对见面没什么期待，感觉还是分了吧……", "timestamp": 1611919684, "type": "text", "url": ""}, {"cid": 1014329, "deleted": false, "image_metadata": {}, "is_dz": true, "name": "洞主", "pid": 202191, "reply_to": -1, "tag": null, "text": "嗯。。。就怕自己分了后又死去活来地到处作贱。", "timestamp": 1611919768, "type": "text", "url": ""}, {"cid": 1014352, "deleted": false, "image_metadata": {}, "is_dz": false, "name": "Carol", "pid": 202191, "reply_to": -1, "tag": null, "text": "人品不差的话凑合过过", "timestamp": 1611919985, "type": "text", "url": ""}, {"cid": 1014369, "deleted": false, "image_metadata": {}, "is_dz": false, "name": "Dave", "pid": 202191, "reply_to": -1, "tag": null, "text": "和我异地的男朋友，话不投机就开吵，互抬杠，，一直都互看不爽，想暴揍对方，但是，如果分手的话，没有人跟我抬杠了，我还难受", "timestamp": 1611920479, "type": "text", "url": ""}, {"cid": 1014677, "deleted": false, "image_metadata": {}, "is_dz": false, "name": "Eve", "pid": 202191, "reply_to": -1, "tag": null, "text": "痛快分吧，别互相耽误。", "timestamp": 1611924672, "type": "text", "url": ""}], "post": {"deleted": false, "image_metadata": {}, "likenum": 1, "pid": 202191, "reply": 6, "tag": null, "text": "和异地女朋友感觉话越来越不投机，见面也就是在各自玩手机，我也觉得她越来越没趣了，这样是不是该分手了", "timestamp": 1611919499, "type": "text", "updated_at": 1611924672, "url": "", "vote": {}}}