{"code": 0, "data": [{"cid": 1017601, "deleted": false, "image_metadata": {}, "is_dz": false, "name": "Alice", "pid": 202668, "reply_to": -1, "tag": null, "text": "dz之前疫情在家从120涨到140，回学校一学期又掉回120，回家快一个月了又有126了", "timestamp": 1611980415, "type": "text", "url": ""}], "post": {"deleted": false, "image_metadata": {}, "likenum": 1, "pid": 202668, "reply": 1, "tag": null, "text": "放纵半年，从115斤涨到145斤，3000米也从11分半变成14分半", "timestamp": 1611979940, "type": "text", "updated_at": 1611980415, "url": "", "vote": {}}}