{"code": 0, "data": [{"cid": 1277176, "deleted": false, "image_metadata": {}, "is_dz": false, "name": "Alice", "pid": 251902, "reply_to": -1, "tag": null, "text": "感觉遇到合适的人了，一起玩一起闹每天都很快乐", "timestamp": 1615979586, "type": "text", "url": ""}, {"cid": 1277187, "deleted": false, "image_metadata": {}, "is_dz": false, "name": "Bob", "pid": 251902, "reply_to": -1, "tag": null, "text": "好！刚和她分手，破防了", "timestamp": 1615979715, "type": "text", "url": ""}, {"cid": 1277243, "deleted": false, "image_metadata": {}, "is_dz": false, "name": "Carol", "pid": 251902, "reply_to": -1, "tag": null, "text": "合理极了", "timestamp": 1615980215, "type": "text", "url": ""}, {"cid": 1277301, "deleted": false, "image_metadata": {}, "is_dz": false, "name": "Dave", "pid": 251902, "reply_to": -1, "tag": null, "text": "哎，就是基本每次见面都超级开心，相互尊重体谅关爱吧", "timestamp": 1615980998, "type": "text", "url": ""}, {"cid": 1277331, "deleted": false, "image_metadata": {}, "is_dz": true, "name": "洞主", "pid": 251902, "reply_to": -1, "tag": null, "text": "Re Dave: 是如何可以如此久的 ", "timestamp": 1615981245, "type": "text", "url": ""}, {"cid": 1277339, "deleted": false, "image_metadata": {}, "is_dz": true, "name": "洞主", "pid": 251902, "reply_to": -1, "tag": null, "text": "Re Alice: 我一直挺好奇，如何确定高中那个人就是“合适的人”？人长大，经历也会改变，喜欢的特征也会不同。会不会因为初中/高中谈了这位，而错过了一些更合适，灵魂上更互补的人", "timestamp": 1615981378, "type": "text", "url": ""}, {"cid": 1277458, "deleted": false, "image_metadata": {}, "is_dz": false, "name": "Eve", "pid": 251902, "reply_to": -1, "tag": null, "text": "感觉爱是会消失的", "timestamp": 1615982471, "type": "text", "url": ""}, {"cid": 1277509, "deleted": false, "image_metadata": {}, "is_dz": false, "name": "Francis", "pid": 251902, "reply_to": -1, "tag": null, "text": "Re 洞主:第二个问题：会", "timestamp": 1615982871, "type": "text", "url": ""}, {"cid": 1277536, "deleted": false, "image_metadata": {}, "is_dz": false, "name": "Grace", "pid": 251902, "reply_to": -1, "tag": null, "text": "不需要寻找最合适的那个，珍惜眼下的这个，把握住了，你们就慢慢成为最适合彼此的人。", "timestamp": 1615983162, "type": "text", "url": ""}, {"cid": 1286426, "deleted": false, "image_metadata": {}, "is_dz": false, "name": "Dave", "pid": 251902, "reply_to": -1, "tag": null, "text": "Re 洞主: 我俩脾气都算好的，如果生气了也不是撒泼吵架而是好好说话，错的那一方会立马怂掉道歉。自己的一些缺点也愿意慢慢改掉，也愿意听对方说话。只是俩人正好合适罢了，换个对象没准儿会很快分手的", "timestamp": 1616064374, "type": "text", "url": ""}], "post": {"deleted": false, "image_metadata": {}, "likenum": 4, "pid": 251902, "reply": 10, "tag": null, "text": "一直很想知道从高中谈四五年甚至更久恋爱的朋友们是什么心态", "timestamp": 1615979375, "type": "text", "updated_at": 1616064374, "url": "", "vote": {}}}