{"code": 0, "data": [{"cid": 1385979, "deleted": false, "image_metadata": {}, "is_dz": true, "name": "洞主", "pid": 272177, "reply_to": -1, "tag": null, "text": "或者说，现在离京还需要审批吗(", "timestamp": 1617459703, "type": "text", "url": ""}, {"cid": 1385982, "deleted": false, "image_metadata": {}, "is_dz": false, "name": "Alice", "pid": 272177, "reply_to": -1, "tag": null, "text": "不用", "timestamp": 1617459722, "type": "text", "url": ""}, {"cid": 1386414, "deleted": false, "image_metadata": {}, "is_dz": false, "name": "Bob", "pid": 272177, "reply_to": -1, "tag": null, "text": "看院系 问辅导员", "timestamp": 1617462917, "type": "text", "url": ""}], "post": {"deleted": false, "image_metadata": {}, "likenum": 3, "pid": 272177, "reply": 3, "tag": null, "text": "现在离京审批严吗？比如五一出去玩之类的审批能批下来吗(", "timestamp": 1617459621, "type": "text", "updated_at": 1617462919, "url": "", "vote": {}}}