{"code": 0, "data": [{"cid": 723600, "deleted": false, "image_metadata": {}, "is_dz": false, "name": "Alice", "pid": 150874, "reply_to": -1, "tag": null, "text": "我全都要！", "timestamp": 1608134317, "type": "text", "url": ""}, {"cid": 723602, "deleted": false, "image_metadata": {}, "is_dz": true, "name": "洞主", "pid": 150874, "reply_to": -1, "tag": null, "text": "但是毕竟时间精力经济有限啊…", "timestamp": 1608134346, "type": "text", "url": ""}, {"cid": 723721, "deleted": false, "image_metadata": {}, "is_dz": false, "name": "Bob", "pid": 150874, "reply_to": -1, "tag": null, "text": "自私的Bob选择前者", "timestamp": 1608135243, "type": "text", "url": ""}, {"cid": 723893, "deleted": false, "image_metadata": {}, "is_dz": true, "name": "洞主", "pid": 150874, "reply_to": -1, "tag": null, "text": "Re Bob: 我一直都是前者…但最近在反思了", "timestamp": 1608136728, "type": "text", "url": ""}, {"cid": 724383, "deleted": false, "image_metadata": {}, "is_dz": false, "name": "Bob", "pid": 150874, "reply_to": -1, "tag": null, "text": "Re 洞主: 可能因为Bob真的没办法和喜欢自己但自己不喜欢的人在一起qaq 这前提下再对人家好就很像在耽误人家 巨难", "timestamp": 1608150656, "type": "text", "url": ""}, {"cid": 725588, "deleted": false, "image_metadata": {}, "is_dz": false, "name": "Carol", "pid": 150874, "reply_to": -1, "tag": null, "text": "其实是有办法避免后者的存在的\n", "timestamp": 1608182827, "type": "text", "url": ""}, {"cid": 726379, "deleted": false, "image_metadata": {}, "is_dz": true, "name": "洞主", "pid": 150874, "reply_to": -1, "tag": null, "text": "Re Carol: ？？？", "timestamp": 1608193479, "type": "text", "url": ""}], "post": {"deleted": false, "image_metadata": {}, "likenum": 4, "pid": 150874, "reply": 7, "tag": null, "text": "应该对自己喜欢的人好，还是应该对喜欢自己的人好？\n非常矛盾。", "timestamp": 1608134289, "type": "text", "updated_at": 1608193481, "url": "", "vote": {}}}