{"code": 0, "data": [{"cid": 201516, "deleted": false, "image_metadata": {}, "is_dz": false, "name": "Alice", "pid": 36255, "reply_to": -1, "tag": null, "text": "98都不舍得买 来树洞当乞丐？", "timestamp": 1596331420, "type": "text", "url": ""}, {"cid": 201518, "deleted": false, "image_metadata": {}, "is_dz": true, "name": "洞主", "pid": 36255, "reply_to": -1, "tag": null, "text": "乞丐？纯粹只是不想在游戏上花钱而已", "timestamp": 1596331457, "type": "text", "url": ""}, {"cid": 201521, "deleted": false, "image_metadata": {}, "is_dz": false, "name": "Bob", "pid": 36255, "reply_to": -1, "tag": null, "text": "这…这要是发在贴吧里会被喷死的，dz体会一下吧", "timestamp": 1596331543, "type": "text", "url": ""}, {"cid": 201522, "deleted": false, "image_metadata": {}, "is_dz": false, "name": "Carol", "pid": 36255, "reply_to": -1, "tag": null, "text": "Re 洞主: 那不还是乞丐吗", "timestamp": 1596331556, "type": "text", "url": ""}, {"cid": 201523, "deleted": false, "image_metadata": {}, "is_dz": false, "name": "Dave", "pid": 36255, "reply_to": -1, "tag": null, "text": "Re Bob: 我也想喷dz(._.)", "timestamp": 1596331572, "type": "text", "url": ""}, {"cid": 201526, "deleted": false, "image_metadata": {}, "is_dz": false, "name": "Eve", "pid": 36255, "reply_to": -1, "tag": null, "text": "那就不要玩呀 或者云玩家 或者和平精英 哪有吃饭不给钱的道理的呢", "timestamp": 1596331609, "type": "text", "url": ""}, {"cid": 201528, "deleted": false, "image_metadata": {}, "is_dz": true, "name": "洞主", "pid": 36255, "reply_to": -1, "tag": null, "text": "好叭，我好以为借steam账号很正常，是我想多了", "timestamp": 1596331701, "type": "text", "url": ""}, {"cid": 201531, "deleted": false, "image_metadata": {}, "is_dz": false, "name": "Francis", "pid": 36255, "reply_to": -1, "tag": null, "text": "Re 洞主: 游戏和任何商品都一样的……论文下载还要钱的", "timestamp": 1596331906, "type": "text", "url": ""}, {"cid": 201545, "deleted": false, "image_metadata": {}, "is_dz": false, "name": "Grace", "pid": 36255, "reply_to": -1, "tag": null, "text": "不建议玩，现在玩的就三类人，主播，外挂，职业选手，其他占比很小了", "timestamp": 1596332451, "type": "text", "url": ""}, {"cid": 201547, "deleted": false, "image_metadata": {}, "is_dz": false, "name": "Grace", "pid": 36255, "reply_to": -1, "tag": null, "text": "他们主播把把要遇到孤儿的", "timestamp": 1596332517, "type": "text", "url": ""}, {"cid": 201561, "deleted": false, "image_metadata": {}, "is_dz": false, "name": "Hans", "pid": 36255, "reply_to": -1, "tag": null, "text": "我的号 好久没玩了，可以借你", "timestamp": 1596332870, "type": "text", "url": ""}, {"cid": 201573, "deleted": false, "image_metadata": {}, "is_dz": true, "name": "洞主", "pid": 36255, "reply_to": -1, "tag": null, "text": "谢啦Hans，我要是真想借号，我为啥不在朋友圈借，这里借了肯定联系不到呀，我只是发发牢骚，结果被人喷，哈哈，挺气的", "timestamp": 1596333481, "type": "text", "url": ""}, {"cid": 201588, "deleted": false, "image_metadata": {}, "is_dz": false, "name": "Isabella", "pid": 36255, "reply_to": -1, "tag": null, "text": "洞主俺可以借你号 咱可以一起玩", "timestamp": 1596334080, "type": "text", "url": ""}, {"cid": 201616, "deleted": false, "image_metadata": {}, "is_dz": false, "name": "Jason", "pid": 36255, "reply_to": -1, "tag": null, "text": "\"或者有人可以借下steam账号吗\"\n\"这里借了肯定联系不到啊，我只是发发牢骚\"", "timestamp": 1596334916, "type": "text", "url": ""}, {"cid": 201684, "deleted": false, "image_metadata": {}, "is_dz": false, "name": "Kate", "pid": 36255, "reply_to": -1, "tag": null, "text": "steam账号比微信账号还重要吧。。。很多用户里面的游戏都好几千的哪能那么轻易借给你", "timestamp": 1596336411, "type": "text", "url": ""}, {"cid": 201773, "deleted": false, "image_metadata": {}, "is_dz": false, "name": "Louis", "pid": 36255, "reply_to": -1, "tag": null, "text": "steam账号可不是那么容易借的", "timestamp": 1596338465, "type": "text", "url": ""}, {"cid": 201798, "deleted": false, "image_metadata": {}, "is_dz": false, "name": "Margaret", "pid": 36255, "reply_to": -1, "tag": null, "text": "尊重版权，享受了就要付费...没人教过你在超市拿东西了要付钱吗", "timestamp": 1596339197, "type": "text", "url": ""}, {"cid": 201942, "deleted": false, "image_metadata": {}, "is_dz": true, "name": "洞主", "pid": 36255, "reply_to": -1, "tag": null, "text": "Re Margaret: 没人教过，抱歉，这个难道还用教？", "timestamp": 1596341692, "type": "text", "url": ""}], "post": {"deleted": false, "image_metadata": {}, "likenum": 11, "pid": 36255, "reply": 18, "tag": null, "text": "特别想玩PUBG ，但是又不太想花钱买？该怎么办？或者有人可以借下steam账号吗", "timestamp": 1596331268, "type": "text", "updated_at": 1606782599, "url": "", "vote": {}}}