{"code": 0, "data": [{"cid": 1495860, "deleted": false, "image_metadata": {}, "is_dz": false, "name": "Alice", "pid": 294226, "reply_to": -1, "tag": null, "text": "大家都在往小了换，是不是要集合成一个鞋池，成功率会更高哈哈哈", "timestamp": 1618999211, "type": "text", "url": ""}, {"cid": 1496338, "deleted": false, "image_metadata": {}, "is_dz": false, "name": "Bob", "pid": 294226, "reply_to": 1495860, "tag": null, "text": "Re Alice: 不太可能，因为女生的鞋码以37，38居多，而39偏少，所以必定在这一层断层。（男生一般都要40以上了）。 ", "timestamp": 1619002719, "type": "text", "url": ""}], "post": {"deleted": false, "image_metadata": {}, "likenum": 1, "pid": 294226, "reply": 2, "tag": null, "text": "校庆鞋脚踏实地款 38换37 只试穿了一下QAQ\n联系方式qq：928958167", "timestamp": 1618999164, "type": "text", "updated_at": 1619002719, "url": "", "vote": {}}}