{"code": 0, "data": [{"cid": 2641873, "deleted": false, "image_metadata": {}, "is_dz": true, "name": "洞主", "pid": 504239, "reply_to": -1, "tag": null, "text": "对了dz不用qq 希望好心的dy可以邮件发下微信号！", "timestamp": 1633162041, "type": "text", "url": ""}], "post": {"deleted": false, "image_metadata": {}, "likenum": 2, "pid": 504239, "reply": 1, "tag": null, "text": "正在申美国的cs master 2022 fall，已找中介，转码选手 唯一长处是英文水平超高 想认识一下同申cs master的洞友一起交流一下选校、网申和文书的事情qwq（尤其是网申中遇到的小问题和互相交流ps？）邮箱是1749406553@qq.com", "timestamp": 1633161200, "type": "text", "updated_at": 1633162042, "url": "", "vote": {}}}