{"code": 0, "data": [{"cid": 1712543, "deleted": false, "image_metadata": {}, "is_dz": false, "name": "Alice", "pid": 336798, "reply_to": -1, "tag": null, "text": "+1呜呜", "timestamp": 1621782907, "type": "text", "url": ""}, {"cid": 1712607, "deleted": false, "image_metadata": {}, "is_dz": false, "name": "Bob", "pid": 336798, "reply_to": -1, "tag": null, "text": "差点以为是我自己发的", "timestamp": 1621783637, "type": "text", "url": ""}], "post": {"deleted": false, "image_metadata": {}, "likenum": 1, "pid": 336798, "reply": 2, "tag": null, "text": "没作业写的时候好无聊 为什么从没有人我我的提问箱提问\n果然是我太闲了", "timestamp": 1621781438, "type": "text", "updated_at": 1621783636, "url": "", "vote": {}}}