{"code": 0, "data": [{"cid": 3003192, "deleted": false, "image_metadata": {}, "is_dz": false, "name": "Alice", "pid": 568882, "reply_to": -1, "tag": null, "text": "毛少肾虚？", "timestamp": 1637513421, "type": "text", "url": ""}, {"cid": 3003193, "deleted": false, "image_metadata": {}, "is_dz": false, "name": "Bob", "pid": 568882, "reply_to": -1, "tag": null, "text": "我女朋友嫌我腿毛多..", "timestamp": 1637513431, "type": "text", "url": ""}, {"cid": 3003195, "deleted": false, "image_metadata": {}, "is_dz": true, "name": "洞主", "pid": 568882, "reply_to": -1, "tag": null, "text": "dz只有很少的腿毛、腋毛", "timestamp": 1637513436, "type": "text", "url": ""}, {"cid": 3003198, "deleted": false, "image_metadata": {}, "is_dz": false, "name": "Carol", "pid": 568882, "reply_to": 3003192, "tag": null, "text": "Re Alice: 真的吗", "timestamp": 1637513450, "type": "text", "url": ""}, {"cid": 3003204, "deleted": false, "image_metadata": {}, "is_dz": false, "name": "Alice", "pid": 568882, "reply_to": 3003198, "tag": null, "text": "Re Carol: 假的 我胡诌的", "timestamp": 1637513493, "type": "text", "url": ""}, {"cid": 3003308, "deleted": false, "image_metadata": {}, "is_dz": false, "name": "Dave", "pid": 568882, "reply_to": -1, "tag": null, "text": "超爱腿毛", "timestamp": 1637514086, "type": "text", "url": ""}, {"cid": 3003337, "deleted": false, "image_metadata": {}, "is_dz": true, "name": "洞主", "pid": 568882, "reply_to": 3003308, "tag": null, "text": "Re Dave: 女生吗", "timestamp": 1637514345, "type": "text", "url": ""}, {"cid": 3003611, "deleted": false, "image_metadata": {}, "is_dz": false, "name": "Eve", "pid": 568882, "reply_to": -1, "tag": null, "text": "女生喜欢长的帅的", "timestamp": 1637516601, "type": "text", "url": ""}], "post": {"deleted": false, "image_metadata": {}, "likenum": 3, "pid": 568882, "reply": 8, "tag": "性相关", "text": "女生喜欢毛多的男生还是毛少的，主要是腿毛。\n毛少会不会看起来不够man", "timestamp": 1637513394, "type": "text", "updated_at": 1637516602, "url": "", "vote": {}}}