{"code": 0, "data": [{"cid": 2129840, "deleted": false, "image_metadata": {}, "is_dz": true, "name": "洞主", "pid": 413142, "reply_to": -1, "tag": null, "text": "dz因为辅导员在某些事上的隐瞒/拖延错过了很好的机会", "timestamp": 1627180018, "type": "text", "url": ""}, {"cid": 2129844, "deleted": false, "image_metadata": {}, "is_dz": false, "name": "Alice", "pid": 413142, "reply_to": -1, "tag": null, "text": "我一般这种时候都会扪心自问一下，如果是我能不能做得更好，不能就闭嘴不哔哔", "timestamp": 1627180060, "type": "text", "url": ""}, {"cid": 2129851, "deleted": false, "image_metadata": {}, "is_dz": false, "name": "Bob", "pid": 413142, "reply_to": -1, "tag": null, "text": "补助3000不算少了吧", "timestamp": 1627180133, "type": "text", "url": ""}, {"cid": 2129858, "deleted": false, "image_metadata": {}, "is_dz": false, "name": "Dave", "pid": 413142, "reply_to": -1, "tag": null, "text": "我觉得有些事情fdy也很为难，毕竟不是分内的工作，但是作为一个人又很想关爱小朋友就去做，可是这样长期也未必对小朋友是好事，总有一天小朋友会没有fdy的", "timestamp": 1627180197, "type": "text", "url": ""}, {"cid": 2129865, "deleted": false, "image_metadata": {}, "is_dz": false, "name": "Dave", "pid": 413142, "reply_to": -1, "tag": null, "text": "比如说info上的通知，有些通知辅导员可以不转，毕竟info起到了公告的作用，没看到不是辅导员的责任，并且以后到了社会上也不会有人提醒别人有什么机会", "timestamp": 1627180307, "type": "text", "url": ""}, {"cid": 2129873, "deleted": false, "image_metadata": {}, "is_dz": false, "name": "Dave", "pid": 413142, "reply_to": -1, "tag": null, "text": "再比如说保研的时候fdy也可以不帮小朋友问还有哪个导师有名额，这完全不应该是fdy的工作，可是不这么做小朋友可能就保不上研", "timestamp": 1627180385, "type": "text", "url": ""}, {"cid": 2129876, "deleted": false, "image_metadata": {}, "is_dz": false, "name": "Eve", "pid": 413142, "reply_to": 2129873, "tag": null, "text": "Re Dave: dave说的很对", "timestamp": 1627180451, "type": "text", "url": ""}, {"cid": 2129878, "deleted": false, "image_metadata": {}, "is_dz": false, "name": "Dave", "pid": 413142, "reply_to": -1, "tag": null, "text": "还有在已有明确通知的情况下小朋友错过了ddl可能影响毕业，fdy也本应没有义务去帮小朋友想办法，毕竟都是成年人了，自己该为自己的事情负责，可是fdy出于爱心也可能去帮小朋友想办法", "timestamp": 1627180489, "type": "text", "url": ""}, {"cid": 2129882, "deleted": false, "image_metadata": {}, "is_dz": false, "name": "Dave", "pid": 413142, "reply_to": -1, "tag": null, "text": "所说的这么多例子，如果fdy没有去做，这完全不能怪fdy。当然fdy也会纠结自己做这些事情对小朋友好还是不好", "timestamp": 1627180561, "type": "text", "url": ""}, {"cid": 2129921, "deleted": false, "image_metadata": {}, "is_dz": false, "name": "Francis", "pid": 413142, "reply_to": 2129851, "tag": null, "text": "Re Bob: 助教都差不多能拿到这个钱，但是工作比辅导员少多了", "timestamp": 1627181328, "type": "text", "url": ""}, {"cid": 2130440, "deleted": false, "image_metadata": {}, "is_dz": false, "name": "Bob", "pid": 413142, "reply_to": 2129921, "tag": null, "text": "Re Francis: 有的fdy做的真的还没助教多", "timestamp": 1627187511, "type": "text", "url": ""}, {"cid": 2130456, "deleted": false, "image_metadata": {}, "is_dz": false, "name": "Bob", "pid": 413142, "reply_to": 2129921, "tag": null, "text": "我觉得fdy职位就是用爱发电吧，确实很多事情不做也没违反规定，但是这个岗位本来就不仅仅是一份工作，很多fdy都是为了情怀为了理想在做事，于是一些仅仅满足最低要求的fdy对比之下就有点相形见绌了，但也没有苛责的必要，只能期待自己遇到的是前者。", "timestamp": 1627187629, "type": "text", "url": ""}], "post": {"deleted": false, "image_metadata": {}, "likenum": 6, "pid": 413142, "reply": 12, "tag": null, "text": "大家觉得自己的辅导员有做得不够好的地方吗？我觉得也不是fdy的错，有很多工作软性要求是可以不做的，而fdy硬性工作又很耗时，总结还是学校给fdy的补助太少了吧", "timestamp": 1627179985, "type": "text", "updated_at": 1627187627, "url": "", "vote": {}}}