{"code": 0, "data": [{"cid": 83637, "deleted": false, "image_metadata": {}, "is_dz": false, "name": "Alice", "pid": 14332, "reply_to": -1, "tag": null, "text": "我总觉得给分是随机抽样的", "timestamp": 1593858057, "type": "text", "url": ""}, {"cid": 83642, "deleted": false, "image_metadata": {}, "is_dz": true, "name": "洞主", "pid": 14332, "reply_to": -1, "tag": null, "text": "Re Alice: 传统艺能了", "timestamp": 1593858128, "type": "text", "url": ""}, {"cid": 83724, "deleted": false, "image_metadata": {}, "is_dz": false, "name": "Bob", "pid": 14332, "reply_to": -1, "tag": null, "text": "可能是压力问题…\n我自己有的压力特别大的课反而特别认真，最后都考的很好\n自认为很轻松的课反而常有翻车…", "timestamp": 1593859007, "type": "text", "url": ""}], "post": {"deleted": false, "image_metadata": {}, "likenum": 1, "pid": 14332, "reply": 3, "tag": null, "text": "一门学得超累很怕挂科的课得了A，一门自以为做的很好的课得了C，造化弄人，造化弄人", "timestamp": 1593857841, "type": "text", "updated_at": 1606782589, "url": "", "vote": {}}}