{"code": 0, "data": [{"cid": 3142665, "deleted": false, "image_metadata": {}, "is_dz": true, "name": "洞主", "pid": 595217, "reply_to": -1, "tag": null, "text": "直接就并列这两个词", "timestamp": 1639195131, "type": "text", "url": ""}, {"cid": 3142673, "deleted": false, "image_metadata": {}, "is_dz": true, "name": "洞主", "pid": 595217, "reply_to": 3142665, "tag": null, "text": "不知道有没有人看到这个推送，后来被删了", "timestamp": 1639195321, "type": "text", "url": ""}, {"cid": 3142675, "deleted": false, "image_metadata": {}, "is_dz": false, "name": "Alice", "pid": 595217, "reply_to": -1, "tag": null, "text": "恶毒的政治隐喻", "timestamp": 1639195331, "type": "text", "url": ""}, {"cid": 3142676, "deleted": false, "image_metadata": {}, "is_dz": false, "name": "Alice", "pid": 595217, "reply_to": 3142675, "tag": null, "text": "Re Alice: 寻衅滋事⚠️", "timestamp": 1639195343, "type": "text", "url": ""}, {"cid": 3142686, "deleted": false, "image_metadata": {}, "is_dz": false, "name": "Bob", "pid": 595217, "reply_to": -1, "tag": null, "text": "牛逼", "timestamp": 1639195631, "type": "text", "url": ""}, {"cid": 3142707, "deleted": false, "image_metadata": {}, "is_dz": false, "name": "Carol", "pid": 595217, "reply_to": -1, "tag": null, "text": "这也太狂了", "timestamp": 1639196570, "type": "text", "url": ""}, {"cid": 3142716, "deleted": false, "image_metadata": {}, "is_dz": false, "name": "Dave", "pid": 595217, "reply_to": -1, "tag": null, "text": "这不是劝诫小朋友养成良好习惯的箴言吗，为什么危啊，多好。要我说就应该写成标语贴在每个小学，印成小册子发给每一个大学生。", "timestamp": 1639196762, "type": "text", "url": ""}, {"cid": 3142719, "deleted": false, "image_metadata": {}, "is_dz": false, "name": "Eve", "pid": 595217, "reply_to": 3142716, "tag": null, "text": "Re Dave: sb……", "timestamp": 1639196837, "type": "text", "url": ""}, {"cid": 3142725, "deleted": false, "image_metadata": {}, "is_dz": false, "name": "Francis", "pid": 595217, "reply_to": -1, "tag": null, "text": "支持正义隐喻", "timestamp": 1639197163, "type": "text", "url": ""}, {"cid": 3142726, "deleted": false, "image_metadata": {}, "is_dz": false, "name": "Grace", "pid": 595217, "reply_to": 3142716, "tag": null, "text": "Re Dave: 应该印刷一个敏感用语小册子，全国人民人手一本，告诫大家不要用这些词汇", "timestamp": 1639197170, "type": "text", "url": ""}, {"cid": 3142739, "deleted": false, "image_metadata": {}, "is_dz": false, "name": "Carol", "pid": 595217, "reply_to": 3142716, "tag": null, "text": "Re Dave: 狂！", "timestamp": 1639197397, "type": "text", "url": ""}, {"cid": 3142778, "deleted": false, "image_metadata": {}, "is_dz": false, "name": "Hans", "pid": 595217, "reply_to": -1, "tag": null, "text": "资瓷", "timestamp": 1639199470, "type": "text", "url": ""}, {"cid": 3142786, "deleted": false, "image_metadata": {}, "is_dz": false, "name": "Isabella", "pid": 595217, "reply_to": -1, "tag": null, "text": "这是哪个院系发的？？？", "timestamp": 1639199596, "type": "text", "url": ""}, {"cid": 3142803, "deleted": false, "image_metadata": {"h": 607, "w": 1080}, "is_dz": false, "name": "Jason", "pid": 595217, "reply_to": -1, "tag": null, "text": "", "timestamp": 1639200657, "type": "image", "url": "eq/eqz4udlaiwal4jjm5drqftve5zjfs737.jpeg"}, {"cid": 3142821, "deleted": false, "image_metadata": {}, "is_dz": false, "name": "Bob", "pid": 595217, "reply_to": 3142726, "tag": null, "text": "Re Grace: 那这本册子，光避讳相关的内容就有一个博雅塔高", "timestamp": 1639201658, "type": "text", "url": ""}], "post": {"deleted": false, "image_metadata": {}, "likenum": 11, "pid": 595217, "reply": 15, "tag": "政治相关", "text": "毛病不改，积恶成习\nnmmd太哈人了，这个是某系的推送", "timestamp": 1639195089, "type": "text", "updated_at": 1639201657, "url": "", "vote": {}}}