{"code": 0, "data": [{"cid": 963778, "deleted": false, "image_metadata": {}, "is_dz": false, "name": "Alice", "pid": 195359, "reply_to": -1, "tag": null, "text": "退出成绩单 再打开一次", "timestamp": 1611332523, "type": "text", "url": ""}, {"cid": 963787, "deleted": false, "image_metadata": {}, "is_dz": false, "name": "Alice", "pid": 195359, "reply_to": -1, "tag": null, "text": "或者可以在设置里强制重新登录", "timestamp": 1611332539, "type": "text", "url": ""}, {"cid": 963826, "deleted": false, "image_metadata": {}, "is_dz": false, "name": "Bob", "pid": 195359, "reply_to": -1, "tag": null, "text": "我还是不行，难道因为bob是研究生嘛", "timestamp": 1611332685, "type": "text", "url": ""}, {"cid": 963904, "deleted": false, "image_metadata": {}, "is_dz": true, "name": "洞主", "pid": 195359, "reply_to": -1, "tag": null, "text": "Re Alice: 尝试了alice的两种方式并且切换了流量和WiFi都不行，不过还是十分感谢alice～", "timestamp": 1611333028, "type": "text", "url": ""}, {"cid": 963910, "deleted": false, "image_metadata": {}, "is_dz": true, "name": "洞主", "pid": 195359, "reply_to": -1, "tag": null, "text": "Re Bob: dz也是研究生，可能真的是这个原因?", "timestamp": 1611333047, "type": "text", "url": ""}, {"cid": 964092, "deleted": false, "image_metadata": {}, "is_dz": false, "name": "Alice", "pid": 195359, "reply_to": -1, "tag": null, "text": "呜呜，那我就不知道了……", "timestamp": 1611333936, "type": "text", "url": ""}], "post": {"deleted": false, "image_metadata": {}, "likenum": 2, "pid": 195359, "reply": 6, "tag": null, "text": "下载了THUinfo后点成绩单显示的是网络异常，请重试，请问这个怎么解决呀?", "timestamp": 1611332368, "type": "text", "updated_at": 1611333935, "url": "", "vote": {}}}