{"code": 0, "data": [{"cid": 946034, "deleted": false, "image_metadata": {}, "is_dz": false, "name": "Alice", "pid": 192134, "reply_to": -1, "tag": null, "text": "我爸妈也说你都是死肥猪了还吃", "timestamp": 1611203347, "type": "text", "url": ""}, {"cid": 946046, "deleted": false, "image_metadata": {}, "is_dz": false, "name": "Bob", "pid": 192134, "reply_to": -1, "tag": null, "text": "我的妈，我爸妈完全相反.....各种认为多吃是福.....", "timestamp": 1611203492, "type": "text", "url": ""}, {"cid": 946051, "deleted": false, "image_metadata": {}, "is_dz": false, "name": "Carol", "pid": 192134, "reply_to": -1, "tag": null, "text": "我爸妈觉得我胖 然而一到吃饭就让我多吃...", "timestamp": 1611203572, "type": "text", "url": ""}, {"cid": 946054, "deleted": false, "image_metadata": {}, "is_dz": false, "name": "Dave", "pid": 192134, "reply_to": -1, "tag": null, "text": "Re Bob: 一样的。。", "timestamp": 1611203585, "type": "text", "url": ""}, {"cid": 946055, "deleted": false, "image_metadata": {}, "is_dz": false, "name": "Dave", "pid": 192134, "reply_to": -1, "tag": null, "text": "Re Carol: 回错了...和carol一样惨", "timestamp": 1611203606, "type": "text", "url": ""}, {"cid": 946070, "deleted": false, "image_metadata": {}, "is_dz": false, "name": "Eve", "pid": 192134, "reply_to": -1, "tag": null, "text": "Re Carol: 不差这一顿！", "timestamp": 1611203735, "type": "text", "url": ""}, {"cid": 946090, "deleted": false, "image_metadata": {}, "is_dz": true, "name": "洞主", "pid": 192134, "reply_to": -1, "tag": null, "text": "Re Carol: 吃完再减肥！", "timestamp": 1611204002, "type": "text", "url": ""}, {"cid": 946091, "deleted": false, "image_metadata": {}, "is_dz": false, "name": "Francis", "pid": 192134, "reply_to": -1, "tag": null, "text": "我胖了10kg，我爸妈终于不叨叨我瘦了要好好吃了，他们终于感觉我减肥也没问题了", "timestamp": 1611204004, "type": "text", "url": ""}, {"cid": 946097, "deleted": false, "image_metadata": {}, "is_dz": true, "name": "洞主", "pid": 192134, "reply_to": -1, "tag": null, "text": "dz不胖但是长痘严重，爸妈就希望我喝粥不吃辣等等，但作为我自己我可以接受少量长痘换来吃美食的权利呜呜呜", "timestamp": 1611204053, "type": "text", "url": ""}, {"cid": 946107, "deleted": false, "image_metadata": {}, "is_dz": false, "name": "Grace", "pid": 192134, "reply_to": -1, "tag": null, "text": "好吃的不一定就辣呀，蟹粉豆腐，黑椒牛仔骨，砂锅焗鸡翅，都可以不辣的", "timestamp": 1611204161, "type": "text", "url": ""}, {"cid": 946538, "deleted": false, "image_metadata": {}, "is_dz": true, "name": "洞主", "pid": 192134, "reply_to": -1, "tag": null, "text": "Re Grace: dz试试", "timestamp": 1611208671, "type": "text", "url": ""}, {"cid": 946540, "deleted": false, "image_metadata": {}, "is_dz": true, "name": "洞主", "pid": 192134, "reply_to": -1, "tag": null, "text": "Re Grace: 谢谢Grace！", "timestamp": 1611208699, "type": "text", "url": ""}], "post": {"deleted": false, "image_metadata": {}, "likenum": 3, "pid": 192134, "reply": 12, "tag": null, "text": "回家来爸妈对饮食的限制真的绝了，我愿意丑着但让自己吃的开心点，就十恶不赦让你们丢脸了呗", "timestamp": 1611203312, "type": "text", "updated_at": 1611208701, "url": "", "vote": {}}}