{"code": 0, "data": [{"cid": 378164, "deleted": false, "image_metadata": {}, "is_dz": false, "name": "Alice", "pid": 77324, "reply_to": -1, "tag": null, "text": "为你点一个赞", "timestamp": 1600760630, "type": "text", "url": ""}, {"cid": 378166, "deleted": false, "image_metadata": {}, "is_dz": false, "name": "Bob", "pid": 77324, "reply_to": -1, "tag": null, "text": "啊啊啊戳到了(┯_┯)", "timestamp": 1600760642, "type": "text", "url": ""}, {"cid": 378192, "deleted": false, "image_metadata": {}, "is_dz": false, "name": "Carol", "pid": 77324, "reply_to": -1, "tag": null, "text": "没懂啥意思", "timestamp": 1600761071, "type": "text", "url": ""}], "post": {"deleted": false, "image_metadata": {}, "likenum": 2, "pid": 77324, "reply": 3, "tag": null, "text": "迈着虚晃的步子到卫生间洗手，看了一眼在楼道里不知所措的保洁，她似乎想了很久下定决心，站在卫生间门口跟我说：先前楼道里有个冰箱，放了两个多星期，我不知道要不要，你能帮我问问ta们要不要吗？\n我对那个放了很久的冰箱有记忆，我说：好啊，我帮你问问。\n我看楼道里没有冰箱了，不知道是哪一间宿舍，转头：您是把冰箱拿下去了吗？\n“嗯是啊……”ta又解释了一番，很急。\n“您还记得是哪一间宿舍吗？”她指了指：“好像是这个吧？我也忘了……”\n敲了两次门，终于找对宿舍了。跟住里面的同学说了，ta出来感谢阿姨。\n\n就只是单纯的觉得，每个人都有他的不容易。心疼保洁。\n很多口头上的理所当然在一些人身上很不容易。be kind to one another.\n", "timestamp": 1600760535, "type": "text", "updated_at": 1606782620, "url": "", "vote": {}}}