{"code": 0, "data": [{"cid": 143393, "deleted": false, "image_metadata": {}, "is_dz": false, "name": "Alice", "pid": 24855, "reply_to": -1, "tag": null, "text": "蹲", "timestamp": 1594973169, "type": "text", "url": ""}, {"cid": 143525, "deleted": false, "image_metadata": {}, "is_dz": false, "name": "Bob", "pid": 24855, "reply_to": -1, "tag": null, "text": "立花是池面不过据说比较严，日下部不错，二外四给了我93，两个老师都主要日语上课不过日下部说的好一点", "timestamp": 1594974681, "type": "text", "url": ""}, {"cid": 143591, "deleted": false, "image_metadata": {}, "is_dz": false, "name": "Carol", "pid": 24855, "reply_to": -1, "tag": null, "text": "立花老师帅啊，而且经常放动画片", "timestamp": 1594975606, "type": "text", "url": ""}], "post": {"deleted": false, "image_metadata": {}, "likenum": 8, "pid": 24855, "reply": 3, "tag": null, "text": "求日语二外立花老师与日下部老师的测评", "timestamp": 1594972742, "type": "text", "updated_at": 1606782593, "url": "", "vote": {}}}