{"code": 0, "data": [{"cid": 503568, "deleted": false, "image_metadata": {}, "is_dz": false, "name": "Alice", "pid": 104800, "reply_to": -1, "tag": null, "text": "学校对面的微笑时刻", "timestamp": 1604067524, "type": "text", "url": ""}, {"cid": 503603, "deleted": false, "image_metadata": {}, "is_dz": false, "name": "Bob", "pid": 104800, "reply_to": -1, "tag": null, "text": "天真蓝 海马体", "timestamp": 1604068360, "type": "text", "url": ""}, {"cid": 503626, "deleted": false, "image_metadata": {}, "is_dz": false, "name": "Carol", "pid": 104800, "reply_to": -1, "tag": null, "text": "天真蓝～ ", "timestamp": 1604069048, "type": "text", "url": ""}, {"cid": 503717, "deleted": false, "image_metadata": {}, "is_dz": true, "name": "洞主", "pid": 104800, "reply_to": -1, "tag": null, "text": "谢谢dym", "timestamp": 1604070967, "type": "text", "url": ""}, {"cid": 503718, "deleted": false, "image_metadata": {}, "is_dz": true, "name": "洞主", "pid": 104800, "reply_to": -1, "tag": null, "text": "我去美团上找找", "timestamp": 1604070978, "type": "text", "url": ""}], "post": {"deleted": false, "image_metadata": {}, "likenum": 3, "pid": 104800, "reply": 5, "tag": null, "text": "求问大家求职时证件照都去哪拍的呀？有推荐的么", "timestamp": 1604067500, "type": "text", "updated_at": 1606782637, "url": "", "vote": {}}}