{"code": 0, "data": [{"cid": 2091362, "deleted": false, "image_metadata": {}, "is_dz": false, "name": "Alice", "pid": 406988, "reply_to": -1, "tag": null, "text": "细说", "timestamp": 1626609773, "type": "text", "url": ""}, {"cid": 2091363, "deleted": false, "image_metadata": {}, "is_dz": false, "name": "Bob", "pid": 406988, "reply_to": -1, "tag": null, "text": "展开说说", "timestamp": 1626609776, "type": "text", "url": ""}, {"cid": 2091370, "deleted": false, "image_metadata": {}, "is_dz": false, "name": "Carol", "pid": 406988, "reply_to": -1, "tag": null, "text": "好好奇", "timestamp": 1626609908, "type": "text", "url": ""}, {"cid": 2091371, "deleted": false, "image_metadata": {}, "is_dz": false, "name": "Dave", "pid": 406988, "reply_to": -1, "tag": null, "text": "这不是正常的事么 别怂", "timestamp": 1626609944, "type": "text", "url": ""}, {"cid": 2091418, "deleted": false, "image_metadata": {}, "is_dz": true, "name": "洞主", "pid": 406988, "reply_to": -1, "tag": null, "text": "谈话纪要：一、注意身体，注意卫生，控制频率。二、快找个女朋友。三、询问了包皮翻开情况和私处卫生有关问题。", "timestamp": 1626610539, "type": "text", "url": ""}, {"cid": 2091435, "deleted": false, "image_metadata": {}, "is_dz": false, "name": "Eve", "pid": 406988, "reply_to": -1, "tag": null, "text": "Re 洞主: \n# 快找女朋友", "timestamp": 1626610718, "type": "text", "url": ""}, {"cid": 2091437, "deleted": false, "image_metadata": {}, "is_dz": true, "name": "洞主", "pid": 406988, "reply_to": -1, "tag": null, "text": "还好手机藏的快没造成更大的问题", "timestamp": 1626610750, "type": "text", "url": ""}, {"cid": 2091445, "deleted": false, "image_metadata": {}, "is_dz": false, "name": "Eve", "pid": 406988, "reply_to": 2091437, "tag": null, "text": "Re 洞主: “难道你空想着就能撸？你的意淫对象是谁”", "timestamp": 1626610845, "type": "text", "url": ""}, {"cid": 2091457, "deleted": false, "image_metadata": {}, "is_dz": false, "name": "Francis", "pid": 406988, "reply_to": -1, "tag": null, "text": "你爸真可爱哈哈哈", "timestamp": 1626611045, "type": "text", "url": ""}, {"cid": 2092928, "deleted": false, "image_metadata": {}, "is_dz": false, "name": "Grace", "pid": 406988, "reply_to": -1, "tag": null, "text": "快找女朋友xs", "timestamp": 1626625640, "type": "text", "url": ""}], "post": {"deleted": false, "image_metadata": {}, "likenum": 5, "pid": 406988, "reply": 10, "tag": "性相关", "text": "#406877 老爹找dz谈话了5555", "timestamp": 1626609706, "type": "text", "updated_at": 1626625641, "url": "", "vote": {}}}