{"code": 0, "data": [{"cid": 55426, "deleted": false, "image_metadata": {}, "is_dz": false, "name": "Alice", "pid": 9309, "reply_to": -1, "tag": null, "text": "为啥还要申硕士", "timestamp": 1593278547, "type": "text", "url": ""}, {"cid": 55609, "deleted": false, "image_metadata": {}, "is_dz": false, "name": "Bob", "pid": 9309, "reply_to": -1, "tag": null, "text": "这里应该大多数是本科…", "timestamp": 1593280942, "type": "text", "url": ""}, {"cid": 55985, "deleted": false, "image_metadata": {}, "is_dz": false, "name": "Carol", "pid": 9309, "reply_to": -1, "tag": null, "text": "本科没好好学习硕士咋上的你清哈哈哈", "timestamp": 1593308585, "type": "text", "url": ""}, {"cid": 57163, "deleted": false, "image_metadata": {}, "is_dz": false, "name": "Dave", "pid": 9309, "reply_to": -1, "tag": null, "text": "本科 gpa 不到 3，不敢说话", "timestamp": 1593326511, "type": "text", "url": ""}], "post": {"deleted": false, "image_metadata": {}, "likenum": 4, "pid": 9309, "reply": 4, "tag": null, "text": "硕士毕业再申请硕士的时候能用硕士gpa和文章来弥补本科gpa吗 \n本科华科 绩点3.5 硕士清华 绩点3.8 2篇一作文章 一篇一区一篇三区 雅思7.0 托福108\n马上研三了，不打算申请美国了，想申请英国g5级别的学校，方向可能会换一下。本科硕士都是学物理的，申请物理电子交叉类的学科硕士。\n\n后悔本科没好好学习。硕士毕业再申请硕士还看重本科gpa吗。", "timestamp": 1593278031, "type": "text", "updated_at": 1606782588, "url": "", "vote": {}}}