{"code": 0, "data": [{"cid": 1682447, "deleted": false, "image_metadata": {}, "is_dz": false, "name": "Alice", "pid": 330486, "reply_to": -1, "tag": null, "text": "四个都有", "timestamp": 1621351665, "type": "text", "url": ""}], "post": {"deleted": false, "image_metadata": {}, "likenum": 2, "pid": 330486, "reply": 1, "tag": "政治相关", "text": "你认为中国目前的较为富裕的中产及以上的家庭是因为____________达到了现在的地位", "timestamp": 1621351539, "type": "text", "updated_at": 1621351667, "url": "", "vote": {"vote_data": {"勤劳、拼搏与头脑": 7, "作奸犯科与破坏规则": 1, "特权、社会关系与家庭出身": 21, "运气与政策红利": 26}, "vote_options": ["勤劳、拼搏与头脑", "作奸犯科与破坏规则", "特权、社会关系与家庭出身", "运气与政策红利"]}}}