{"code": 0, "data": [{"cid": 1805337, "deleted": false, "image_metadata": {}, "is_dz": false, "name": "Alice", "pid": 354648, "reply_to": -1, "tag": null, "text": "未来走研发 -> 深研院\n未来走算法 -> 深研院的牛导 或者 中科院", "timestamp": 1623066250, "type": "text", "url": ""}, {"cid": 1805918, "deleted": false, "image_metadata": {}, "is_dz": true, "name": "洞主", "pid": 354648, "reply_to": 1805337, "tag": null, "text": "Re Alice: 研发是什么？软件吗", "timestamp": 1623072000, "type": "text", "url": ""}, {"cid": 1806515, "deleted": false, "image_metadata": {}, "is_dz": false, "name": "Alice", "pid": 354648, "reply_to": 1805918, "tag": null, "text": "Re 洞主: 嗯嗯嗯，软件这个说法有点太宽泛了，包括前端后端客户端等很多类型开发/研发岗", "timestamp": 1623077200, "type": "text", "url": ""}], "post": {"deleted": false, "image_metadata": {}, "likenum": 0, "pid": 354648, "reply": 3, "tag": null, "text": "cs读硕哪个更香？", "timestamp": 1623063631, "type": "text", "updated_at": 1623077198, "url": "", "vote": {"vote_data": {"深研院": 73, "中科院": 44}, "vote_options": ["深研院", "中科院"]}}}