{"code": 0, "data": [{"cid": 1322218, "deleted": false, "image_metadata": {}, "is_dz": false, "name": "Alice", "pid": 260107, "reply_to": -1, "tag": null, "text": "操场跑几圈", "timestamp": 1616565950, "type": "text", "url": ""}, {"cid": 1322334, "deleted": false, "image_metadata": {}, "is_dz": true, "name": "洞主", "pid": 260107, "reply_to": -1, "tag": null, "text": "Re Alice: 难道不会越运动越想吗", "timestamp": 1616566947, "type": "text", "url": ""}, {"cid": 1331275, "deleted": false, "image_metadata": {}, "is_dz": true, "name": "洞主", "pid": 260107, "reply_to": -1, "tag": null, "text": "dz现在难耐了", "timestamp": 1616673627, "type": "text", "url": ""}], "post": {"deleted": false, "image_metadata": {}, "likenum": 1, "pid": 260107, "reply": 3, "tag": "性相关", "text": "#性相关\ndz ♂ wonder 0\n想知道除了yp 还有啥可以满足x需求的办法吗……感觉手冲没啥效果，yp又怕得病……\n", "timestamp": 1616565796, "type": "text", "updated_at": 1616673628, "url": "", "vote": {}}}