{"code": 0, "data": [{"cid": 1403626, "deleted": false, "image_metadata": {}, "is_dz": false, "name": "Alice", "pid": 275448, "reply_to": -1, "tag": null, "text": "同，而且说了也不听，下次还会", "timestamp": 1617726422, "type": "text", "url": ""}, {"cid": 1403632, "deleted": false, "image_metadata": {}, "is_dz": false, "name": "Bob", "pid": 275448, "reply_to": -1, "tag": null, "text": "因为他们醒着的时候就觉得所有人都没睡", "timestamp": 1617726492, "type": "text", "url": ""}], "post": {"deleted": false, "image_metadata": {}, "likenum": 0, "pid": 275448, "reply": 2, "tag": null, "text": "为什么总有人这么晚也会在楼道或者浴室里大声说笑啊？而且为什么非要半夜洗澡/洗衣服啊？洗就算了，为什么能心安理得在那大声讲话啊？无语", "timestamp": 1617726256, "type": "text", "updated_at": 1617726490, "url": "", "vote": {}}}