{"code": 0, "data": [{"cid": 1404670, "deleted": false, "image_metadata": {}, "is_dz": false, "name": "Alice", "pid": 275637, "reply_to": -1, "tag": null, "text": "光速抽查", "timestamp": 1617761044, "type": "text", "url": ""}, {"cid": 1404672, "deleted": false, "image_metadata": {}, "is_dz": false, "name": "Bob", "pid": 275637, "reply_to": -1, "tag": null, "text": "按照相对论，如果草得够快，你甚至能草到自己？", "timestamp": 1617761083, "type": "text", "url": ""}, {"cid": 1404676, "deleted": false, "image_metadata": {}, "is_dz": false, "name": "Carol", "pid": 275637, "reply_to": -1, "tag": null, "text": "Re Bob: 光速做圆周运动", "timestamp": 1617761130, "type": "text", "url": ""}], "post": {"deleted": false, "image_metadata": {}, "likenum": 1, "pid": 275637, "reply": 3, "tag": "性相关", "text": "#性相关\n利用相对论来延长自己的时间（doge）", "timestamp": 1617760935, "type": "text", "updated_at": 1617761131, "url": "", "vote": {}}}